[
  {
    "date": "2026-02-03",
    "period": "afternoon",
    "location_name": "berry_head",
    "latitude": 50.402568,
    "longitude": -3.481143,
    "vis_score": NaN,
    "vis_rag": "Red",
    "score_wind": 0.0,
    "score_rain": 0.375
  },
  {
    "date": "2026-02-03",
    "period": "morning",
    "location_name": "berry_head",
    "latitude": 50.402568,
    "longitude": -3.481143,
    "vis_score": NaN,
    "vis_rag": "Red",
    "score_wind": 0.16666666666666666,
    "score_rain": 0.6666666666666666
  },
  {
    "date": "2026-02-03",
    "period": "afternoon",
    "location_name": "branscombe",
    "latitude": 50.683979,
    "longitude": -3.116856,
    "vis_score": NaN,
    "vis_rag": "Red",
    "score_wind": 0.0625,
    "score_rain": 0.575
  },
  {
    "date": "2026-02-03",
    "period": "morning",
    "location_name": "branscombe",
    "latitude": 50.683979,
    "longitude": -3.116856,
    "vis_score": NaN,
    "vis_rag": "Red",
    "score_wind": 0.3333333333333333,
    "score_rain": 0.9333333333333332
  },
  {
    "date": "2026-02-03",
    "period": "afternoon",
    "location_name": "bude",
    "latitude": 50.817853,
    "longitude": -4.560764,
    "vis_score": NaN,
    "vis_rag": "Red",
    "score_wind": 0.5,
    "score_rain": 0.125
  },
  {
    "date": "2026-02-03",
    "period": "morning",
    "location_name": "bude",
    "latitude": 50.817853,
    "longitude": -4.560764,
    "vis_score": NaN,
    "vis_rag": "Red",
    "score_wind": 0.8333333333333334,
    "score_rain": 0.6666666666666666
  },
  {
    "date": "2026-02-03",
    "period": "afternoon",
    "location_name": "dodman_point",
    "latitude": 50.222568,
    "longitude": -4.806776,
    "vis_score": NaN,
    "vis_rag": "Red",
    "score_wind": 0.1875,
    "score_rain": 0.625
  },
  {
    "date": "2026-02-03",
    "period": "morning",
    "location_name": "dodman_point",
    "latitude": 50.222568,
    "longitude": -4.806776,
    "vis_score": NaN,
    "vis_rag": "Red",
    "score_wind": 0.25,
    "score_rain": 0.8333333333333334
  },
  {
    "date": "2026-02-03",
    "period": "afternoon",
    "location_name": "falmouth",
    "latitude": 50.152573,
    "longitude": -5.06627,
    "vis_score": NaN,
    "vis_rag": "Red",
    "score_wind": 0.1875,
    "score_rain": 0.5
  },
  {
    "date": "2026-02-03",
    "period": "morning",
    "location_name": "falmouth",
    "latitude": 50.152573,
    "longitude": -5.06627,
    "vis_score": NaN,
    "vis_rag": "Red",
    "score_wind": 0.25,
    "score_rain": 0.5
  },
  {
    "date": "2026-02-03",
    "period": "afternoon",
    "location_name": "fishermans_cove",
    "latitude": 50.238151,
    "longitude": -5.371382,
    "vis_score": NaN,
    "vis_rag": "Red",
    "score_wind": 0.75,
    "score_rain": 0.375
  },
  {
    "date": "2026-02-03",
    "period": "morning",
    "location_name": "fishermans_cove",
    "latitude": 50.238151,
    "longitude": -5.371382,
    "vis_score": NaN,
    "vis_rag": "Red",
    "score_wind": 0.6666666666666666,
    "score_rain": 0.75
  },
  {
    "date": "2026-02-03",
    "period": "afternoon",
    "location_name": "isle_portland",
    "latitude": 50.521858,
    "longitude": -2.44875,
    "vis_score": NaN,
    "vis_rag": "Red",
    "score_wind": 0.3125,
    "score_rain": 0.4375
  },
  {
    "date": "2026-02-03",
    "period": "morning",
    "location_name": "isle_portland",
    "latitude": 50.521858,
    "longitude": -2.44875,
    "vis_score": NaN,
    "vis_rag": "Red",
    "score_wind": 0.6666666666666666,
    "score_rain": 1.0
  },
  {
    "date": "2026-02-03",
    "period": "afternoon",
    "location_name": "lannacombe",
    "latitude": 50.221171,
    "longitude": -3.680452,
    "vis_score": NaN,
    "vis_rag": "Red",
    "score_wind": 0.0,
    "score_rain": 0.1875
  },
  {
    "date": "2026-02-03",
    "period": "morning",
    "location_name": "lannacombe",
    "latitude": 50.221171,
    "longitude": -3.680452,
    "vis_score": NaN,
    "vis_rag": "Red",
    "score_wind": 0.0,
    "score_rain": 0.5833333333333334
  },
  {
    "date": "2026-02-03",
    "period": "afternoon",
    "location_name": "start_point",
    "latitude": 50.229288,
    "longitude": -3.65076,
    "vis_score": NaN,
    "vis_rag": "Red",
    "score_wind": 0.5,
    "score_rain": 0.1875
  },
  {
    "date": "2026-02-03",
    "period": "morning",
    "location_name": "start_point",
    "latitude": 50.229288,
    "longitude": -3.65076,
    "vis_score": NaN,
    "vis_rag": "Red",
    "score_wind": 0.8333333333333334,
    "score_rain": 0.5833333333333334
  },
  {
    "date": "2026-02-03",
    "period": "afternoon",
    "location_name": "thurlestone",
    "latitude": 50.263044,
    "longitude": -3.870057,
    "vis_score": NaN,
    "vis_rag": "Red",
    "score_wind": 0.0,
    "score_rain": 0.3125
  },
  {
    "date": "2026-02-03",
    "period": "morning",
    "location_name": "thurlestone",
    "latitude": 50.263044,
    "longitude": -3.870057,
    "vis_score": NaN,
    "vis_rag": "Red",
    "score_wind": 0.3333333333333333,
    "score_rain": 0.25
  },
  {
    "date": "2026-02-03",
    "period": "afternoon",
    "location_name": "towan_beach",
    "latitude": 50.157088,
    "longitude": -4.984155,
    "vis_score": NaN,
    "vis_rag": "Red",
    "score_wind": 0.125,
    "score_rain": 0.4375
  },
  {
    "date": "2026-02-03",
    "period": "morning",
    "location_name": "towan_beach",
    "latitude": 50.157088,
    "longitude": -4.984155,
    "vis_score": NaN,
    "vis_rag": "Red",
    "score_wind": 0.25,
    "score_rain": 0.5
  },
  {
    "date": "2026-02-04",
    "period": "afternoon",
    "location_name": "berry_head",
    "latitude": 50.402568,
    "longitude": -3.481143,
    "vis_score": NaN,
    "vis_rag": "Red",
    "score_wind": 0.5625,
    "score_rain": 0.375
  },
  {
    "date": "2026-02-04",
    "period": "morning",
    "location_name": "berry_head",
    "latitude": 50.402568,
    "longitude": -3.481143,
    "vis_score": NaN,
    "vis_rag": "Red",
    "score_wind": 0.375,
    "score_rain": 0.1875
  },
  {
    "date": "2026-02-04",
    "period": "afternoon",
    "location_name": "branscombe",
    "latitude": 50.683979,
    "longitude": -3.116856,
    "vis_score": NaN,
    "vis_rag": "Red",
    "score_wind": 0.5625,
    "score_rain": 0.625
  },
  {
    "date": "2026-02-04",
    "period": "morning",
    "location_name": "branscombe",
    "latitude": 50.683979,
    "longitude": -3.116856,
    "vis_score": NaN,
    "vis_rag": "Red",
    "score_wind": 0.0625,
    "score_rain": 0.375
  },
  {
    "date": "2026-02-04",
    "period": "afternoon",
    "location_name": "bude",
    "latitude": 50.817853,
    "longitude": -4.560764,
    "vis_score": NaN,
    "vis_rag": "Red",
    "score_wind": 0.625,
    "score_rain": 0.5
  },
  {
    "date": "2026-02-04",
    "period": "morning",
    "location_name": "bude",
    "latitude": 50.817853,
    "longitude": -4.560764,
    "vis_score": NaN,
    "vis_rag": "Red",
    "score_wind": 0.5,
    "score_rain": 0.1875
  },
  {
    "date": "2026-02-04",
    "period": "afternoon",
    "location_name": "dodman_point",
    "latitude": 50.222568,
    "longitude": -4.806776,
    "vis_score": NaN,
    "vis_rag": "Red",
    "score_wind": 0.625,
    "score_rain": 0.4375
  },
  {
    "date": "2026-02-04",
    "period": "morning",
    "location_name": "dodman_point",
    "latitude": 50.222568,
    "longitude": -4.806776,
    "vis_score": NaN,
    "vis_rag": "Red",
    "score_wind": 0.25,
    "score_rain": 0.1875
  },
  {
    "date": "2026-02-04",
    "period": "afternoon",
    "location_name": "falmouth",
    "latitude": 50.152573,
    "longitude": -5.06627,
    "vis_score": NaN,
    "vis_rag": "Red",
    "score_wind": 0.625,
    "score_rain": 0.4375
  },
  {
    "date": "2026-02-04",
    "period": "morning",
    "location_name": "falmouth",
    "latitude": 50.152573,
    "longitude": -5.06627,
    "vis_score": NaN,
    "vis_rag": "Red",
    "score_wind": 0.25,
    "score_rain": 0.5
  },
  {
    "date": "2026-02-04",
    "period": "afternoon",
    "location_name": "fishermans_cove",
    "latitude": 50.238151,
    "longitude": -5.371382,
    "vis_score": NaN,
    "vis_rag": "Red",
    "score_wind": 1.0,
    "score_rain": 0.5625
  },
  {
    "date": "2026-02-04",
    "period": "morning",
    "location_name": "fishermans_cove",
    "latitude": 50.238151,
    "longitude": -5.371382,
    "vis_score": NaN,
    "vis_rag": "Red",
    "score_wind": 0.375,
    "score_rain": 0.375
  },
  {
    "date": "2026-02-04",
    "period": "afternoon",
    "location_name": "isle_portland",
    "latitude": 50.521858,
    "longitude": -2.44875,
    "vis_score": NaN,
    "vis_rag": "Red",
    "score_wind": 0.75,
    "score_rain": 0.1875
  },
  {
    "date": "2026-02-04",
    "period": "morning",
    "location_name": "isle_portland",
    "latitude": 50.521858,
    "longitude": -2.44875,
    "vis_score": NaN,
    "vis_rag": "Red",
    "score_wind": 0.1875,
    "score_rain": 0.0
  },
  {
    "date": "2026-02-04",
    "period": "afternoon",
    "location_name": "lannacombe",
    "latitude": 50.221171,
    "longitude": -3.680452,
    "vis_score": NaN,
    "vis_rag": "Red",
    "score_wind": 0.25,
    "score_rain": 0.4375
  },
  {
    "date": "2026-02-04",
    "period": "morning",
    "location_name": "lannacombe",
    "latitude": 50.221171,
    "longitude": -3.680452,
    "vis_score": NaN,
    "vis_rag": "Red",
    "score_wind": 0.125,
    "score_rain": 0.0
  },
  {
    "date": "2026-02-04",
    "period": "afternoon",
    "location_name": "start_point",
    "latitude": 50.229288,
    "longitude": -3.65076,
    "vis_score": NaN,
    "vis_rag": "Red",
    "score_wind": 0.375,
    "score_rain": 0.4375
  },
  {
    "date": "2026-02-04",
    "period": "morning",
    "location_name": "start_point",
    "latitude": 50.229288,
    "longitude": -3.65076,
    "vis_score": NaN,
    "vis_rag": "Red",
    "score_wind": 1.0,
    "score_rain": 0.0
  },
  {
    "date": "2026-02-04",
    "period": "afternoon",
    "location_name": "thurlestone",
    "latitude": 50.263044,
    "longitude": -3.870057,
    "vis_score": NaN,
    "vis_rag": "Red",
    "score_wind": 1.0,
    "score_rain": 0.5
  },
  {
    "date": "2026-02-04",
    "period": "morning",
    "location_name": "thurlestone",
    "latitude": 50.263044,
    "longitude": -3.870057,
    "vis_score": NaN,
    "vis_rag": "Red",
    "score_wind": 0.6875,
    "score_rain": 0.125
  },
  {
    "date": "2026-02-04",
    "period": "afternoon",
    "location_name": "towan_beach",
    "latitude": 50.157088,
    "longitude": -4.984155,
    "vis_score": NaN,
    "vis_rag": "Red",
    "score_wind": 0.375,
    "score_rain": 0.4375
  },
  {
    "date": "2026-02-04",
    "period": "morning",
    "location_name": "towan_beach",
    "latitude": 50.157088,
    "longitude": -4.984155,
    "vis_score": NaN,
    "vis_rag": "Red",
    "score_wind": 0.1875,
    "score_rain": 0.375
  },
  {
    "date": "2026-02-05",
    "period": "afternoon",
    "location_name": "berry_head",
    "latitude": 50.402568,
    "longitude": -3.481143,
    "vis_score": 0.6681123536198791,
    "vis_rag": "Red",
    "score_wind": 0.3125,
    "score_rain": 0.95
  },
  {
    "date": "2026-02-05",
    "period": "morning",
    "location_name": "berry_head",
    "latitude": 50.402568,
    "longitude": -3.481143,
    "vis_score": 0.6945051087303765,
    "vis_rag": "Red",
    "score_wind": 0.5625,
    "score_rain": 1.0
  },
  {
    "date": "2026-02-05",
    "period": "afternoon",
    "location_name": "branscombe",
    "latitude": 50.683979,
    "longitude": -3.116856,
    "vis_score": 0.5278694478359004,
    "vis_rag": "Red",
    "score_wind": 0.0625,
    "score_rain": 0.875
  },
  {
    "date": "2026-02-05",
    "period": "morning",
    "location_name": "branscombe",
    "latitude": 50.683979,
    "longitude": -3.116856,
    "vis_score": 0.5971979565078495,
    "vis_rag": "Red",
    "score_wind": 0.4375,
    "score_rain": 0.95
  },
  {
    "date": "2026-02-05",
    "period": "afternoon",
    "location_name": "bude",
    "latitude": 50.817853,
    "longitude": -4.560764,
    "vis_score": 0.7763015835368202,
    "vis_rag": "Red",
    "score_wind": 0.375,
    "score_rain": 0.8875
  },
  {
    "date": "2026-02-05",
    "period": "morning",
    "location_name": "bude",
    "latitude": 50.817853,
    "longitude": -4.560764,
    "vis_score": 0.9582261532998896,
    "vis_rag": "Red",
    "score_wind": 0.875,
    "score_rain": 0.9375
  },
  {
    "date": "2026-02-05",
    "period": "afternoon",
    "location_name": "dodman_point",
    "latitude": 50.222568,
    "longitude": -4.806776,
    "vis_score": 0.5045664483811588,
    "vis_rag": "Red",
    "score_wind": 0.0,
    "score_rain": 0.7625
  },
  {
    "date": "2026-02-05",
    "period": "morning",
    "location_name": "dodman_point",
    "latitude": 50.222568,
    "longitude": -4.806776,
    "vis_score": 0.5971979565078495,
    "vis_rag": "Red",
    "score_wind": 0.4375,
    "score_rain": 0.95
  },
  {
    "date": "2026-02-05",
    "period": "afternoon",
    "location_name": "falmouth",
    "latitude": 50.152573,
    "longitude": -5.06627,
    "vis_score": 0.49985618726723535,
    "vis_rag": "Red",
    "score_wind": 0.125,
    "score_rain": 0.9375
  },
  {
    "date": "2026-02-05",
    "period": "morning",
    "location_name": "falmouth",
    "latitude": 50.152573,
    "longitude": -5.06627,
    "vis_score": 0.5276456601362166,
    "vis_rag": "Red",
    "score_wind": 0.3125,
    "score_rain": 0.8125
  },
  {
    "date": "2026-02-05",
    "period": "afternoon",
    "location_name": "fishermans_cove",
    "latitude": 50.238151,
    "longitude": -5.371382,
    "vis_score": 0.5548528285032418,
    "vis_rag": "Red",
    "score_wind": 0.375,
    "score_rain": 0.9
  },
  {
    "date": "2026-02-05",
    "period": "morning",
    "location_name": "fishermans_cove",
    "latitude": 50.238151,
    "longitude": -5.371382,
    "vis_score": 0.6247964290028096,
    "vis_rag": "Red",
    "score_wind": 0.75,
    "score_rain": 0.5
  },
  {
    "date": "2026-02-05",
    "period": "afternoon",
    "location_name": "isle_portland",
    "latitude": 50.521858,
    "longitude": -2.44875,
    "vis_score": 0.43047753168961356,
    "vis_rag": "Red",
    "score_wind": 0.1875,
    "score_rain": 0.875
  },
  {
    "date": "2026-02-05",
    "period": "morning",
    "location_name": "isle_portland",
    "latitude": 50.521858,
    "longitude": -2.44875,
    "vis_score": 0.49979642900280963,
    "vis_rag": "Red",
    "score_wind": 0.375,
    "score_rain": 0.575
  },
  {
    "date": "2026-02-05",
    "period": "afternoon",
    "location_name": "lannacombe",
    "latitude": 50.221171,
    "longitude": -3.680452,
    "vis_score": 0.40987765693542555,
    "vis_rag": "Red",
    "score_wind": 0.125,
    "score_rain": 0.9
  },
  {
    "date": "2026-02-05",
    "period": "morning",
    "location_name": "lannacombe",
    "latitude": 50.221171,
    "longitude": -3.680452,
    "vis_score": 0.4095489833679979,
    "vis_rag": "Red",
    "score_wind": 0.125,
    "score_rain": 0.625
  },
  {
    "date": "2026-02-05",
    "period": "afternoon",
    "location_name": "start_point",
    "latitude": 50.229288,
    "longitude": -3.65076,
    "vis_score": 0.7705607228660134,
    "vis_rag": "Red",
    "score_wind": 0.875,
    "score_rain": 0.8500000000000001
  },
  {
    "date": "2026-02-05",
    "period": "morning",
    "location_name": "start_point",
    "latitude": 50.229288,
    "longitude": -3.65076,
    "vis_score": 0.8469471978694026,
    "vis_rag": "Red",
    "score_wind": 0.8125,
    "score_rain": 0.625
  },
  {
    "date": "2026-02-05",
    "period": "afternoon",
    "location_name": "thurlestone",
    "latitude": 50.263044,
    "longitude": -3.870057,
    "vis_score": 0.5399336413195317,
    "vis_rag": "Red",
    "score_wind": 0.375,
    "score_rain": 0.8375
  },
  {
    "date": "2026-02-05",
    "period": "morning",
    "location_name": "thurlestone",
    "latitude": 50.263044,
    "longitude": -3.870057,
    "vis_score": 0.6038977087424403,
    "vis_rag": "Red",
    "score_wind": 0.4375,
    "score_rain": 0.7
  },
  {
    "date": "2026-02-05",
    "period": "afternoon",
    "location_name": "towan_beach",
    "latitude": 50.157088,
    "longitude": -4.984155,
    "vis_score": 0.3574889517175827,
    "vis_rag": "Red",
    "score_wind": 0.0625,
    "score_rain": 0.8125
  },
  {
    "date": "2026-02-05",
    "period": "morning",
    "location_name": "towan_beach",
    "latitude": 50.157088,
    "longitude": -4.984155,
    "vis_score": 0.42338799704065183,
    "vis_rag": "Red",
    "score_wind": 0.25,
    "score_rain": 0.6875
  },
  {
    "date": "2026-02-06",
    "period": "afternoon",
    "location_name": "berry_head",
    "latitude": 50.402568,
    "longitude": -3.481143,
    "vis_score": 0.5097105210956505,
    "vis_rag": "Red",
    "score_wind": 0.3125,
    "score_rain": 0.1875
  },
  {
    "date": "2026-02-06",
    "period": "morning",
    "location_name": "berry_head",
    "latitude": 50.402568,
    "longitude": -3.481143,
    "vis_score": 0.5682176562623679,
    "vis_rag": "Red",
    "score_wind": 0.125,
    "score_rain": 0.6875
  },
  {
    "date": "2026-02-06",
    "period": "afternoon",
    "location_name": "branscombe",
    "latitude": 50.683979,
    "longitude": -3.116856,
    "vis_score": 0.49012288691397904,
    "vis_rag": "Red",
    "score_wind": 0.0,
    "score_rain": 0.75
  },
  {
    "date": "2026-02-06",
    "period": "morning",
    "location_name": "branscombe",
    "latitude": 50.683979,
    "longitude": -3.116856,
    "vis_score": 0.5147021600001207,
    "vis_rag": "Red",
    "score_wind": 0.0,
    "score_rain": 1.0
  },
  {
    "date": "2026-02-06",
    "period": "afternoon",
    "location_name": "bude",
    "latitude": 50.817853,
    "longitude": -4.560764,
    "vis_score": 0.5509711764680721,
    "vis_rag": "Red",
    "score_wind": 0.25,
    "score_rain": 0.4375
  },
  {
    "date": "2026-02-06",
    "period": "morning",
    "location_name": "bude",
    "latitude": 50.817853,
    "longitude": -4.560764,
    "vis_score": 0.6147231670092437,
    "vis_rag": "Red",
    "score_wind": 0.0,
    "score_rain": 0.75
  },
  {
    "date": "2026-02-06",
    "period": "afternoon",
    "location_name": "dodman_point",
    "latitude": 50.222568,
    "longitude": -4.806776,
    "vis_score": 0.433994577889731,
    "vis_rag": "Red",
    "score_wind": 0.1875,
    "score_rain": 0.5625
  },
  {
    "date": "2026-02-06",
    "period": "morning",
    "location_name": "dodman_point",
    "latitude": 50.222568,
    "longitude": -4.806776,
    "vis_score": 0.4636902504943472,
    "vis_rag": "Red",
    "score_wind": 0.0,
    "score_rain": 0.875
  },
  {
    "date": "2026-02-06",
    "period": "afternoon",
    "location_name": "falmouth",
    "latitude": 50.152573,
    "longitude": -5.06627,
    "vis_score": 0.4603834104018857,
    "vis_rag": "Red",
    "score_wind": 0.25,
    "score_rain": 0.4375
  },
  {
    "date": "2026-02-06",
    "period": "morning",
    "location_name": "falmouth",
    "latitude": 50.152573,
    "longitude": -5.06627,
    "vis_score": 0.5064468894591796,
    "vis_rag": "Red",
    "score_wind": 0.25,
    "score_rain": 0.75
  },
  {
    "date": "2026-02-06",
    "period": "afternoon",
    "location_name": "fishermans_cove",
    "latitude": 50.238151,
    "longitude": -5.371382,
    "vis_score": 0.5250615369749801,
    "vis_rag": "Red",
    "score_wind": 0.5,
    "score_rain": 0.45
  },
  {
    "date": "2026-02-06",
    "period": "morning",
    "location_name": "fishermans_cove",
    "latitude": 50.238151,
    "longitude": -5.371382,
    "vis_score": 0.5504931690662914,
    "vis_rag": "Red",
    "score_wind": 0.125,
    "score_rain": 0.9375
  },
  {
    "date": "2026-02-06",
    "period": "afternoon",
    "location_name": "isle_portland",
    "latitude": 50.521858,
    "longitude": -2.44875,
    "vis_score": 0.42982664813527227,
    "vis_rag": "Red",
    "score_wind": 0.125,
    "score_rain": 0.375
  },
  {
    "date": "2026-02-06",
    "period": "morning",
    "location_name": "isle_portland",
    "latitude": 50.521858,
    "longitude": -2.44875,
    "vis_score": 0.46443631065904645,
    "vis_rag": "Red",
    "score_wind": 0.0625,
    "score_rain": 0.825
  },
  {
    "date": "2026-02-06",
    "period": "afternoon",
    "location_name": "lannacombe",
    "latitude": 50.221171,
    "longitude": -3.680452,
    "vis_score": 0.35360997369801334,
    "vis_rag": "Red",
    "score_wind": 0.0,
    "score_rain": 0.375
  },
  {
    "date": "2026-02-06",
    "period": "morning",
    "location_name": "lannacombe",
    "latitude": 50.221171,
    "longitude": -3.680452,
    "vis_score": 0.37891738818379256,
    "vis_rag": "Red",
    "score_wind": 0.0,
    "score_rain": 0.625
  },
  {
    "date": "2026-02-06",
    "period": "afternoon",
    "location_name": "start_point",
    "latitude": 50.229288,
    "longitude": -3.65076,
    "vis_score": 0.619520900885548,
    "vis_rag": "Red",
    "score_wind": 0.75,
    "score_rain": 0.375
  },
  {
    "date": "2026-02-06",
    "period": "morning",
    "location_name": "start_point",
    "latitude": 50.229288,
    "longitude": -3.65076,
    "vis_score": 0.6479274102000241,
    "vis_rag": "Red",
    "score_wind": 0.125,
    "score_rain": 0.6375
  },
  {
    "date": "2026-02-06",
    "period": "afternoon",
    "location_name": "thurlestone",
    "latitude": 50.263044,
    "longitude": -3.870057,
    "vis_score": 0.4229006515862801,
    "vis_rag": "Red",
    "score_wind": 0.125,
    "score_rain": 0.6875
  },
  {
    "date": "2026-02-06",
    "period": "morning",
    "location_name": "thurlestone",
    "latitude": 50.263044,
    "longitude": -3.870057,
    "vis_score": 0.4945290642927282,
    "vis_rag": "Red",
    "score_wind": 0.0,
    "score_rain": 0.6875
  },
  {
    "date": "2026-02-06",
    "period": "afternoon",
    "location_name": "towan_beach",
    "latitude": 50.157088,
    "longitude": -4.984155,
    "vis_score": 0.37172232919737214,
    "vis_rag": "Red",
    "score_wind": 0.125,
    "score_rain": 0.4375
  },
  {
    "date": "2026-02-06",
    "period": "morning",
    "location_name": "towan_beach",
    "latitude": 50.157088,
    "longitude": -4.984155,
    "vis_score": 0.40803381506579484,
    "vis_rag": "Red",
    "score_wind": 0.0,
    "score_rain": 0.8875
  },
  {
    "date": "2026-02-07",
    "period": "afternoon",
    "location_name": "berry_head",
    "latitude": 50.402568,
    "longitude": -3.481143,
    "vis_score": 0.49645923342228115,
    "vis_rag": "Red",
    "score_wind": 0.375,
    "score_rain": 0.25
  },
  {
    "date": "2026-02-07",
    "period": "morning",
    "location_name": "berry_head",
    "latitude": 50.402568,
    "longitude": -3.481143,
    "vis_score": 0.509418144875561,
    "vis_rag": "Red",
    "score_wind": 0.375,
    "score_rain": 0.95
  },
  {
    "date": "2026-02-07",
    "period": "afternoon",
    "location_name": "branscombe",
    "latitude": 50.683979,
    "longitude": -3.116856,
    "vis_score": 0.46049739731674677,
    "vis_rag": "Red",
    "score_wind": 0.125,
    "score_rain": 0.8125
  },
  {
    "date": "2026-02-07",
    "period": "morning",
    "location_name": "branscombe",
    "latitude": 50.683979,
    "longitude": -3.116856,
    "vis_score": 0.4531983025213255,
    "vis_rag": "Red",
    "score_wind": 0.125,
    "score_rain": 0.6875
  },
  {
    "date": "2026-02-07",
    "period": "afternoon",
    "location_name": "bude",
    "latitude": 50.817853,
    "longitude": -4.560764,
    "vis_score": 0.5258749167234655,
    "vis_rag": "Red",
    "score_wind": 0.1875,
    "score_rain": 0.6875
  },
  {
    "date": "2026-02-07",
    "period": "morning",
    "location_name": "bude",
    "latitude": 50.817853,
    "longitude": -4.560764,
    "vis_score": 0.5358044315660528,
    "vis_rag": "Red",
    "score_wind": 0.375,
    "score_rain": 0.875
  },
  {
    "date": "2026-02-07",
    "period": "afternoon",
    "location_name": "dodman_point",
    "latitude": 50.222568,
    "longitude": -4.806776,
    "vis_score": 0.43742866405129766,
    "vis_rag": "Red",
    "score_wind": 0.125,
    "score_rain": 0.75
  },
  {
    "date": "2026-02-07",
    "period": "morning",
    "location_name": "dodman_point",
    "latitude": 50.222568,
    "longitude": -4.806776,
    "vis_score": 0.4178535081260951,
    "vis_rag": "Red",
    "score_wind": 0.0625,
    "score_rain": 0.75
  },
  {
    "date": "2026-02-07",
    "period": "afternoon",
    "location_name": "falmouth",
    "latitude": 50.152573,
    "longitude": -5.06627,
    "vis_score": 0.5141241314803302,
    "vis_rag": "Red",
    "score_wind": 0.75,
    "score_rain": 0.5
  },
  {
    "date": "2026-02-07",
    "period": "morning",
    "location_name": "falmouth",
    "latitude": 50.152573,
    "longitude": -5.06627,
    "vis_score": 0.4639121413516245,
    "vis_rag": "Red",
    "score_wind": 0.125,
    "score_rain": 0.9375
  },
  {
    "date": "2026-02-07",
    "period": "afternoon",
    "location_name": "fishermans_cove",
    "latitude": 50.238151,
    "longitude": -5.371382,
    "vis_score": 0.6001353897665085,
    "vis_rag": "Red",
    "score_wind": 0.5,
    "score_rain": 0.625
  },
  {
    "date": "2026-02-07",
    "period": "morning",
    "location_name": "fishermans_cove",
    "latitude": 50.238151,
    "longitude": -5.371382,
    "vis_score": 0.5676132445255103,
    "vis_rag": "Red",
    "score_wind": 0.5,
    "score_rain": 0.95
  },
  {
    "date": "2026-02-07",
    "period": "afternoon",
    "location_name": "isle_portland",
    "latitude": 50.521858,
    "longitude": -2.44875,
    "vis_score": 0.39086865237241797,
    "vis_rag": "Red",
    "score_wind": 0.25,
    "score_rain": 0.1875
  },
  {
    "date": "2026-02-07",
    "period": "morning",
    "location_name": "isle_portland",
    "latitude": 50.521858,
    "longitude": -2.44875,
    "vis_score": 0.39601265153306814,
    "vis_rag": "Red",
    "score_wind": 0.25,
    "score_rain": 0.6875
  },
  {
    "date": "2026-02-07",
    "period": "afternoon",
    "location_name": "lannacombe",
    "latitude": 50.221171,
    "longitude": -3.680452,
    "vis_score": 0.35135213150057865,
    "vis_rag": "Red",
    "score_wind": 0.125,
    "score_rain": 0.25
  },
  {
    "date": "2026-02-07",
    "period": "morning",
    "location_name": "lannacombe",
    "latitude": 50.221171,
    "longitude": -3.680452,
    "vis_score": 0.35405143765032776,
    "vis_rag": "Red",
    "score_wind": 0.0625,
    "score_rain": 0.9375
  },
  {
    "date": "2026-02-07",
    "period": "afternoon",
    "location_name": "start_point",
    "latitude": 50.229288,
    "longitude": -3.65076,
    "vis_score": 0.6565135347845884,
    "vis_rag": "Red",
    "score_wind": 0.75,
    "score_rain": 0.25
  },
  {
    "date": "2026-02-07",
    "period": "morning",
    "location_name": "start_point",
    "latitude": 50.229288,
    "longitude": -3.65076,
    "vis_score": 0.641882767938056,
    "vis_rag": "Red",
    "score_wind": 0.75,
    "score_rain": 0.95
  },
  {
    "date": "2026-02-07",
    "period": "afternoon",
    "location_name": "thurlestone",
    "latitude": 50.263044,
    "longitude": -3.870057,
    "vis_score": 0.4389509570972209,
    "vis_rag": "Red",
    "score_wind": 0.1875,
    "score_rain": 0.25
  },
  {
    "date": "2026-02-07",
    "period": "morning",
    "location_name": "thurlestone",
    "latitude": 50.263044,
    "longitude": -3.870057,
    "vis_score": 0.4558869864082256,
    "vis_rag": "Red",
    "score_wind": 0.125,
    "score_rain": 0.9375
  },
  {
    "date": "2026-02-07",
    "period": "afternoon",
    "location_name": "towan_beach",
    "latitude": 50.157088,
    "longitude": -4.984155,
    "vis_score": 0.46908489979487883,
    "vis_rag": "Red",
    "score_wind": 0.75,
    "score_rain": 0.4375
  },
  {
    "date": "2026-02-07",
    "period": "morning",
    "location_name": "towan_beach",
    "latitude": 50.157088,
    "longitude": -4.984155,
    "vis_score": 0.405932368892242,
    "vis_rag": "Red",
    "score_wind": 0.125,
    "score_rain": 1.0
  },
  {
    "date": "2026-02-08",
    "period": "afternoon",
    "location_name": "berry_head",
    "latitude": 50.402568,
    "longitude": -3.481143,
    "vis_score": 0.4050394608414064,
    "vis_rag": "Red",
    "score_wind": 0.125,
    "score_rain": 0.8125
  },
  {
    "date": "2026-02-08",
    "period": "morning",
    "location_name": "berry_head",
    "latitude": 50.402568,
    "longitude": -3.481143,
    "vis_score": 0.41553034275654444,
    "vis_rag": "Red",
    "score_wind": 0.0,
    "score_rain": 0.4375
  },
  {
    "date": "2026-02-08",
    "period": "afternoon",
    "location_name": "branscombe",
    "latitude": 50.683979,
    "longitude": -3.116856,
    "vis_score": 0.41507527170065317,
    "vis_rag": "Red",
    "score_wind": 0.0,
    "score_rain": 1.0
  },
  {
    "date": "2026-02-08",
    "period": "morning",
    "location_name": "branscombe",
    "latitude": 50.683979,
    "longitude": -3.116856,
    "vis_score": 0.4105866637433556,
    "vis_rag": "Red",
    "score_wind": 0.0,
    "score_rain": 0.5
  },
  {
    "date": "2026-02-08",
    "period": "afternoon",
    "location_name": "bude",
    "latitude": 50.817853,
    "longitude": -4.560764,
    "vis_score": 0.43143366226934526,
    "vis_rag": "Red",
    "score_wind": 0.25,
    "score_rain": 0.5
  },
  {
    "date": "2026-02-08",
    "period": "morning",
    "location_name": "bude",
    "latitude": 50.817853,
    "longitude": -4.560764,
    "vis_score": 0.45760501909773393,
    "vis_rag": "Red",
    "score_wind": 0.0,
    "score_rain": 0.4375
  },
  {
    "date": "2026-02-08",
    "period": "afternoon",
    "location_name": "dodman_point",
    "latitude": 50.222568,
    "longitude": -4.806776,
    "vis_score": 0.3715735338427241,
    "vis_rag": "Red",
    "score_wind": 0.125,
    "score_rain": 0.6875
  },
  {
    "date": "2026-02-08",
    "period": "morning",
    "location_name": "dodman_point",
    "latitude": 50.222568,
    "longitude": -4.806776,
    "vis_score": 0.38617827074540884,
    "vis_rag": "Red",
    "score_wind": 0.0,
    "score_rain": 0.375
  },
  {
    "date": "2026-02-08",
    "period": "afternoon",
    "location_name": "falmouth",
    "latitude": 50.152573,
    "longitude": -5.06627,
    "vis_score": 0.4227886471947145,
    "vis_rag": "Red",
    "score_wind": 0.0625,
    "score_rain": 0.5625
  },
  {
    "date": "2026-02-08",
    "period": "morning",
    "location_name": "falmouth",
    "latitude": 50.152573,
    "longitude": -5.06627,
    "vis_score": 0.45894585109382346,
    "vis_rag": "Red",
    "score_wind": 0.0,
    "score_rain": 0.375
  },
  {
    "date": "2026-02-08",
    "period": "afternoon",
    "location_name": "fishermans_cove",
    "latitude": 50.238151,
    "longitude": -5.371382,
    "vis_score": 0.5161029464285541,
    "vis_rag": "Red",
    "score_wind": 0.25,
    "score_rain": 0.875
  },
  {
    "date": "2026-02-08",
    "period": "morning",
    "location_name": "fishermans_cove",
    "latitude": 50.238151,
    "longitude": -5.371382,
    "vis_score": 0.5457270678991157,
    "vis_rag": "Red",
    "score_wind": 0.0,
    "score_rain": 0.4375
  },
  {
    "date": "2026-02-08",
    "period": "afternoon",
    "location_name": "isle_portland",
    "latitude": 50.521858,
    "longitude": -2.44875,
    "vis_score": 0.36033592011503796,
    "vis_rag": "Red",
    "score_wind": 0.0625,
    "score_rain": 0.75
  },
  {
    "date": "2026-02-08",
    "period": "morning",
    "location_name": "isle_portland",
    "latitude": 50.521858,
    "longitude": -2.44875,
    "vis_score": 0.3492965228113988,
    "vis_rag": "Red",
    "score_wind": 0.0,
    "score_rain": 0.6875
  },
  {
    "date": "2026-02-08",
    "period": "afternoon",
    "location_name": "lannacombe",
    "latitude": 50.221171,
    "longitude": -3.680452,
    "vis_score": 0.34386046191517133,
    "vis_rag": "Red",
    "score_wind": 0.0,
    "score_rain": 0.95
  },
  {
    "date": "2026-02-08",
    "period": "morning",
    "location_name": "lannacombe",
    "latitude": 50.221171,
    "longitude": -3.680452,
    "vis_score": 0.31648534813014206,
    "vis_rag": "Red",
    "score_wind": 0.0,
    "score_rain": 0.75
  },
  {
    "date": "2026-02-08",
    "period": "afternoon",
    "location_name": "start_point",
    "latitude": 50.229288,
    "longitude": -3.65076,
    "vis_score": 0.5850146630150277,
    "vis_rag": "Red",
    "score_wind": 0.5,
    "score_rain": 0.8375
  },
  {
    "date": "2026-02-08",
    "period": "morning",
    "location_name": "start_point",
    "latitude": 50.229288,
    "longitude": -3.65076,
    "vis_score": 0.5845649748169705,
    "vis_rag": "Red",
    "score_wind": 0.125,
    "score_rain": 0.7
  },
  {
    "date": "2026-02-08",
    "period": "afternoon",
    "location_name": "thurlestone",
    "latitude": 50.263044,
    "longitude": -3.870057,
    "vis_score": 0.3767004675337746,
    "vis_rag": "Red",
    "score_wind": 0.0625,
    "score_rain": 1.0
  },
  {
    "date": "2026-02-08",
    "period": "morning",
    "location_name": "thurlestone",
    "latitude": 50.263044,
    "longitude": -3.870057,
    "vis_score": 0.37886552969469806,
    "vis_rag": "Red",
    "score_wind": 0.0,
    "score_rain": 0.45
  },
  {
    "date": "2026-02-08",
    "period": "afternoon",
    "location_name": "towan_beach",
    "latitude": 50.157088,
    "longitude": -4.984155,
    "vis_score": 0.3812668738762282,
    "vis_rag": "Red",
    "score_wind": 0.0625,
    "score_rain": 0.5625
  },
  {
    "date": "2026-02-08",
    "period": "morning",
    "location_name": "towan_beach",
    "latitude": 50.157088,
    "longitude": -4.984155,
    "vis_score": 0.4103055793786834,
    "vis_rag": "Red",
    "score_wind": 0.0,
    "score_rain": 0.1875
  },
  {
    "date": "2026-02-09",
    "period": "afternoon",
    "location_name": "berry_head",
    "latitude": 50.402568,
    "longitude": -3.481143,
    "vis_score": 0.4271888451424604,
    "vis_rag": "Red",
    "score_wind": 0.4375,
    "score_rain": 0.825
  },
  {
    "date": "2026-02-09",
    "period": "morning",
    "location_name": "berry_head",
    "latitude": 50.402568,
    "longitude": -3.481143,
    "vis_score": 0.3925018309179348,
    "vis_rag": "Red",
    "score_wind": 0.1875,
    "score_rain": 0.5
  },
  {
    "date": "2026-02-09",
    "period": "afternoon",
    "location_name": "branscombe",
    "latitude": 50.683979,
    "longitude": -3.116856,
    "vis_score": 0.43142960933585206,
    "vis_rag": "Red",
    "score_wind": 0.1875,
    "score_rain": 0.95
  },
  {
    "date": "2026-02-09",
    "period": "morning",
    "location_name": "branscombe",
    "latitude": 50.683979,
    "longitude": -3.116856,
    "vis_score": 0.41650135841162633,
    "vis_rag": "Red",
    "score_wind": 0.0625,
    "score_rain": 0.75
  },
  {
    "date": "2026-02-09",
    "period": "afternoon",
    "location_name": "bude",
    "latitude": 50.817853,
    "longitude": -4.560764,
    "vis_score": 0.4558875088027386,
    "vis_rag": "Red",
    "score_wind": 0.625,
    "score_rain": 0.65
  },
  {
    "date": "2026-02-09",
    "period": "morning",
    "location_name": "bude",
    "latitude": 50.817853,
    "longitude": -4.560764,
    "vis_score": 0.3954345199354964,
    "vis_rag": "Red",
    "score_wind": 0.5,
    "score_rain": 0.4375
  },
  {
    "date": "2026-02-09",
    "period": "afternoon",
    "location_name": "dodman_point",
    "latitude": 50.222568,
    "longitude": -4.806776,
    "vis_score": 0.4311369717593487,
    "vis_rag": "Red",
    "score_wind": 0.25,
    "score_rain": 0.6875
  },
  {
    "date": "2026-02-09",
    "period": "morning",
    "location_name": "dodman_point",
    "latitude": 50.222568,
    "longitude": -4.806776,
    "vis_score": 0.38003745183251725,
    "vis_rag": "Red",
    "score_wind": 0.25,
    "score_rain": 0.875
  },
  {
    "date": "2026-02-09",
    "period": "afternoon",
    "location_name": "falmouth",
    "latitude": 50.152573,
    "longitude": -5.06627,
    "vis_score": 0.46334758897490935,
    "vis_rag": "Red",
    "score_wind": 0.5625,
    "score_rain": 0.6875
  },
  {
    "date": "2026-02-09",
    "period": "morning",
    "location_name": "falmouth",
    "latitude": 50.152573,
    "longitude": -5.06627,
    "vis_score": 0.4167757092222693,
    "vis_rag": "Red",
    "score_wind": 0.25,
    "score_rain": 0.9375
  },
  {
    "date": "2026-02-09",
    "period": "afternoon",
    "location_name": "fishermans_cove",
    "latitude": 50.238151,
    "longitude": -5.371382,
    "vis_score": 0.5603825540744297,
    "vis_rag": "Red",
    "score_wind": 0.5,
    "score_rain": 0.6875
  },
  {
    "date": "2026-02-09",
    "period": "morning",
    "location_name": "fishermans_cove",
    "latitude": 50.238151,
    "longitude": -5.371382,
    "vis_score": 0.5084147330533453,
    "vis_rag": "Red",
    "score_wind": 0.625,
    "score_rain": 0.75
  },
  {
    "date": "2026-02-09",
    "period": "afternoon",
    "location_name": "isle_portland",
    "latitude": 50.521858,
    "longitude": -2.44875,
    "vis_score": 0.35339604506752187,
    "vis_rag": "Red",
    "score_wind": 0.1875,
    "score_rain": 0.7
  },
  {
    "date": "2026-02-09",
    "period": "morning",
    "location_name": "isle_portland",
    "latitude": 50.521858,
    "longitude": -2.44875,
    "vis_score": 0.3534679917756661,
    "vis_rag": "Red",
    "score_wind": 0.0625,
    "score_rain": 0.5625
  },
  {
    "date": "2026-02-09",
    "period": "afternoon",
    "location_name": "lannacombe",
    "latitude": 50.221171,
    "longitude": -3.680452,
    "vis_score": 0.37310551200006803,
    "vis_rag": "Red",
    "score_wind": 0.125,
    "score_rain": 0.6875
  },
  {
    "date": "2026-02-09",
    "period": "morning",
    "location_name": "lannacombe",
    "latitude": 50.221171,
    "longitude": -3.680452,
    "vis_score": 0.34626108743886636,
    "vis_rag": "Red",
    "score_wind": 0.125,
    "score_rain": 0.575
  },
  {
    "date": "2026-02-09",
    "period": "afternoon",
    "location_name": "start_point",
    "latitude": 50.229288,
    "longitude": -3.65076,
    "vis_score": 0.6213597584967108,
    "vis_rag": "Red",
    "score_wind": 0.625,
    "score_rain": 0.6875
  },
  {
    "date": "2026-02-09",
    "period": "morning",
    "location_name": "start_point",
    "latitude": 50.229288,
    "longitude": -3.65076,
    "vis_score": 0.5817899190537693,
    "vis_rag": "Red",
    "score_wind": 0.75,
    "score_rain": 0.5625
  },
  {
    "date": "2026-02-09",
    "period": "afternoon",
    "location_name": "thurlestone",
    "latitude": 50.263044,
    "longitude": -3.870057,
    "vis_score": 0.42291168102781096,
    "vis_rag": "Red",
    "score_wind": 0.5,
    "score_rain": 0.6875
  },
  {
    "date": "2026-02-09",
    "period": "morning",
    "location_name": "thurlestone",
    "latitude": 50.263044,
    "longitude": -3.870057,
    "vis_score": 0.3610668326210547,
    "vis_rag": "Red",
    "score_wind": 0.25,
    "score_rain": 0.5
  },
  {
    "date": "2026-02-09",
    "period": "afternoon",
    "location_name": "towan_beach",
    "latitude": 50.157088,
    "longitude": -4.984155,
    "vis_score": 0.43176430869112614,
    "vis_rag": "Red",
    "score_wind": 0.3125,
    "score_rain": 0.6875
  },
  {
    "date": "2026-02-09",
    "period": "morning",
    "location_name": "towan_beach",
    "latitude": 50.157088,
    "longitude": -4.984155,
    "vis_score": 0.3856123260328632,
    "vis_rag": "Red",
    "score_wind": 0.25,
    "score_rain": 0.9375
  },
  {
    "date": "2026-02-10",
    "period": "afternoon",
    "location_name": "berry_head",
    "latitude": 50.402568,
    "longitude": -3.481143,
    "vis_score": 0.41359187452553814,
    "vis_rag": "Red",
    "score_wind": 0.375,
    "score_rain": 0.825
  },
  {
    "date": "2026-02-10",
    "period": "morning",
    "location_name": "berry_head",
    "latitude": 50.402568,
    "longitude": -3.481143,
    "vis_score": 0.39648339127368126,
    "vis_rag": "Red",
    "score_wind": 0.25,
    "score_rain": 0.25
  },
  {
    "date": "2026-02-10",
    "period": "afternoon",
    "location_name": "branscombe",
    "latitude": 50.683979,
    "longitude": -3.116856,
    "vis_score": 0.4052057320617451,
    "vis_rag": "Red",
    "score_wind": 0.0,
    "score_rain": 0.875
  },
  {
    "date": "2026-02-10",
    "period": "morning",
    "location_name": "branscombe",
    "latitude": 50.683979,
    "longitude": -3.116856,
    "vis_score": 0.4099855625707152,
    "vis_rag": "Red",
    "score_wind": 0.0,
    "score_rain": 0.4375
  },
  {
    "date": "2026-02-10",
    "period": "afternoon",
    "location_name": "bude",
    "latitude": 50.817853,
    "longitude": -4.560764,
    "vis_score": 0.40899607577515784,
    "vis_rag": "Red",
    "score_wind": 0.125,
    "score_rain": 0.9375
  },
  {
    "date": "2026-02-10",
    "period": "morning",
    "location_name": "bude",
    "latitude": 50.817853,
    "longitude": -4.560764,
    "vis_score": 0.4043005379513871,
    "vis_rag": "Red",
    "score_wind": 0.0,
    "score_rain": 0.25
  },
  {
    "date": "2026-02-10",
    "period": "afternoon",
    "location_name": "dodman_point",
    "latitude": 50.222568,
    "longitude": -4.806776,
    "vis_score": 0.3872615191668703,
    "vis_rag": "Red",
    "score_wind": 0.0,
    "score_rain": 0.8125
  },
  {
    "date": "2026-02-10",
    "period": "morning",
    "location_name": "dodman_point",
    "latitude": 50.222568,
    "longitude": -4.806776,
    "vis_score": 0.3890827832307929,
    "vis_rag": "Red",
    "score_wind": 0.0,
    "score_rain": 0.5
  },
  {
    "date": "2026-02-10",
    "period": "afternoon",
    "location_name": "falmouth",
    "latitude": 50.152573,
    "longitude": -5.06627,
    "vis_score": 0.4717834193403557,
    "vis_rag": "Red",
    "score_wind": 0.5,
    "score_rain": 0.825
  },
  {
    "date": "2026-02-10",
    "period": "morning",
    "location_name": "falmouth",
    "latitude": 50.152573,
    "longitude": -5.06627,
    "vis_score": 0.4477973248888864,
    "vis_rag": "Red",
    "score_wind": 0.125,
    "score_rain": 0.5
  },
  {
    "date": "2026-02-10",
    "period": "afternoon",
    "location_name": "fishermans_cove",
    "latitude": 50.238151,
    "longitude": -5.371382,
    "vis_score": 0.5663735102640846,
    "vis_rag": "Red",
    "score_wind": 0.5,
    "score_rain": 0.9375
  },
  {
    "date": "2026-02-10",
    "period": "morning",
    "location_name": "fishermans_cove",
    "latitude": 50.238151,
    "longitude": -5.371382,
    "vis_score": 0.5326948205898364,
    "vis_rag": "Red",
    "score_wind": 0.5,
    "score_rain": 0.5
  },
  {
    "date": "2026-02-10",
    "period": "afternoon",
    "location_name": "isle_portland",
    "latitude": 50.521858,
    "longitude": -2.44875,
    "vis_score": 0.34451071721386767,
    "vis_rag": "Red",
    "score_wind": 0.125,
    "score_rain": 0.8125
  },
  {
    "date": "2026-02-10",
    "period": "morning",
    "location_name": "isle_portland",
    "latitude": 50.521858,
    "longitude": -2.44875,
    "vis_score": 0.3361446144944853,
    "vis_rag": "Red",
    "score_wind": 0.0,
    "score_rain": 0.375
  },
  {
    "date": "2026-02-10",
    "period": "afternoon",
    "location_name": "lannacombe",
    "latitude": 50.221171,
    "longitude": -3.680452,
    "vis_score": 0.36460473602204396,
    "vis_rag": "Red",
    "score_wind": 0.0,
    "score_rain": 0.9375
  },
  {
    "date": "2026-02-10",
    "period": "morning",
    "location_name": "lannacombe",
    "latitude": 50.221171,
    "longitude": -3.680452,
    "vis_score": 0.34529151602289343,
    "vis_rag": "Red",
    "score_wind": 0.0,
    "score_rain": 0.5
  },
  {
    "date": "2026-02-10",
    "period": "afternoon",
    "location_name": "start_point",
    "latitude": 50.229288,
    "longitude": -3.65076,
    "vis_score": 0.5817159178342002,
    "vis_rag": "Red",
    "score_wind": 0.5,
    "score_rain": 0.9375
  },
  {
    "date": "2026-02-10",
    "period": "morning",
    "location_name": "start_point",
    "latitude": 50.229288,
    "longitude": -3.65076,
    "vis_score": 0.5701973794670442,
    "vis_rag": "Red",
    "score_wind": 0.25,
    "score_rain": 0.5
  },
  {
    "date": "2026-02-10",
    "period": "afternoon",
    "location_name": "thurlestone",
    "latitude": 50.263044,
    "longitude": -3.870057,
    "vis_score": 0.3996783607778158,
    "vis_rag": "Red",
    "score_wind": 0.0,
    "score_rain": 0.8875
  },
  {
    "date": "2026-02-10",
    "period": "morning",
    "location_name": "thurlestone",
    "latitude": 50.263044,
    "longitude": -3.870057,
    "vis_score": 0.3908841014476587,
    "vis_rag": "Red",
    "score_wind": 0.0,
    "score_rain": 0.5
  },
  {
    "date": "2026-02-10",
    "period": "afternoon",
    "location_name": "towan_beach",
    "latitude": 50.157088,
    "longitude": -4.984155,
    "vis_score": 0.43033166552862556,
    "vis_rag": "Red",
    "score_wind": 0.375,
    "score_rain": 0.8125
  },
  {
    "date": "2026-02-10",
    "period": "morning",
    "location_name": "towan_beach",
    "latitude": 50.157088,
    "longitude": -4.984155,
    "vis_score": 0.4052093723033866,
    "vis_rag": "Red",
    "score_wind": 0.0,
    "score_rain": 0.625
  },
  {
    "date": "2026-02-11",
    "period": "afternoon",
    "location_name": "berry_head",
    "latitude": 50.402568,
    "longitude": -3.481143,
    "vis_score": 0.5234135613713171,
    "vis_rag": "Red",
    "score_wind": 0.3125,
    "score_rain": 0.7
  },
  {
    "date": "2026-02-11",
    "period": "morning",
    "location_name": "berry_head",
    "latitude": 50.402568,
    "longitude": -3.481143,
    "vis_score": 0.4787615501441708,
    "vis_rag": "Red",
    "score_wind": 0.875,
    "score_rain": 0.75
  },
  {
    "date": "2026-02-11",
    "period": "afternoon",
    "location_name": "branscombe",
    "latitude": 50.683979,
    "longitude": -3.116856,
    "vis_score": 0.3949112552899323,
    "vis_rag": "Red",
    "score_wind": 0.0625,
    "score_rain": 0.6875
  },
  {
    "date": "2026-02-11",
    "period": "morning",
    "location_name": "branscombe",
    "latitude": 50.683979,
    "longitude": -3.116856,
    "vis_score": 0.4091118681318338,
    "vis_rag": "Red",
    "score_wind": 0.0,
    "score_rain": 0.8125
  },
  {
    "date": "2026-02-11",
    "period": "afternoon",
    "location_name": "bude",
    "latitude": 50.817853,
    "longitude": -4.560764,
    "vis_score": 0.3957814567081115,
    "vis_rag": "Red",
    "score_wind": 0.0625,
    "score_rain": 0.3125
  },
  {
    "date": "2026-02-11",
    "period": "morning",
    "location_name": "bude",
    "latitude": 50.817853,
    "longitude": -4.560764,
    "vis_score": 0.42590935906842486,
    "vis_rag": "Red",
    "score_wind": 0.25,
    "score_rain": 0.625
  },
  {
    "date": "2026-02-11",
    "period": "afternoon",
    "location_name": "dodman_point",
    "latitude": 50.222568,
    "longitude": -4.806776,
    "vis_score": 0.3671055466348213,
    "vis_rag": "Red",
    "score_wind": 0.0625,
    "score_rain": 0.6875
  },
  {
    "date": "2026-02-11",
    "period": "morning",
    "location_name": "dodman_point",
    "latitude": 50.222568,
    "longitude": -4.806776,
    "vis_score": 0.38812608754041567,
    "vis_rag": "Red",
    "score_wind": 0.1875,
    "score_rain": 0.3875
  },
  {
    "date": "2026-02-11",
    "period": "afternoon",
    "location_name": "falmouth",
    "latitude": 50.152573,
    "longitude": -5.06627,
    "vis_score": 0.5779292902973749,
    "vis_rag": "Red",
    "score_wind": 0.25,
    "score_rain": 0.6875
  },
  {
    "date": "2026-02-11",
    "period": "morning",
    "location_name": "falmouth",
    "latitude": 50.152573,
    "longitude": -5.06627,
    "vis_score": 0.5462414744269795,
    "vis_rag": "Red",
    "score_wind": 1.0,
    "score_rain": 0.8125
  },
  {
    "date": "2026-02-11",
    "period": "afternoon",
    "location_name": "fishermans_cove",
    "latitude": 50.238151,
    "longitude": -5.371382,
    "vis_score": 0.6138331339829759,
    "vis_rag": "Red",
    "score_wind": 0.375,
    "score_rain": 0.6375
  },
  {
    "date": "2026-02-11",
    "period": "morning",
    "location_name": "fishermans_cove",
    "latitude": 50.238151,
    "longitude": -5.371382,
    "vis_score": 0.6069515381787188,
    "vis_rag": "Red",
    "score_wind": 0.875,
    "score_rain": 0.625
  },
  {
    "date": "2026-02-11",
    "period": "afternoon",
    "location_name": "isle_portland",
    "latitude": 50.521858,
    "longitude": -2.44875,
    "vis_score": 0.36881789671320453,
    "vis_rag": "Red",
    "score_wind": 0.125,
    "score_rain": 0.6875
  },
  {
    "date": "2026-02-11",
    "period": "morning",
    "location_name": "isle_portland",
    "latitude": 50.521858,
    "longitude": -2.44875,
    "vis_score": 0.37096239497638916,
    "vis_rag": "Red",
    "score_wind": 0.25,
    "score_rain": 0.5625
  },
  {
    "date": "2026-02-11",
    "period": "afternoon",
    "location_name": "lannacombe",
    "latitude": 50.221171,
    "longitude": -3.680452,
    "vis_score": 0.39652420386198944,
    "vis_rag": "Red",
    "score_wind": 0.0625,
    "score_rain": 0.7
  },
  {
    "date": "2026-02-11",
    "period": "morning",
    "location_name": "lannacombe",
    "latitude": 50.221171,
    "longitude": -3.680452,
    "vis_score": 0.39354544406884046,
    "vis_rag": "Red",
    "score_wind": 0.5625,
    "score_rain": 0.4375
  },
  {
    "date": "2026-02-11",
    "period": "afternoon",
    "location_name": "start_point",
    "latitude": 50.229288,
    "longitude": -3.65076,
    "vis_score": 0.6004536201790318,
    "vis_rag": "Red",
    "score_wind": 0.375,
    "score_rain": 0.7
  },
  {
    "date": "2026-02-11",
    "period": "morning",
    "location_name": "start_point",
    "latitude": 50.229288,
    "longitude": -3.65076,
    "vis_score": 0.5998639732479469,
    "vis_rag": "Red",
    "score_wind": 0.875,
    "score_rain": 0.4375
  },
  {
    "date": "2026-02-11",
    "period": "afternoon",
    "location_name": "thurlestone",
    "latitude": 50.263044,
    "longitude": -3.870057,
    "vis_score": 0.38653317605024523,
    "vis_rag": "Red",
    "score_wind": 0.0625,
    "score_rain": 0.7
  },
  {
    "date": "2026-02-11",
    "period": "morning",
    "location_name": "thurlestone",
    "latitude": 50.263044,
    "longitude": -3.870057,
    "vis_score": 0.40273680456939387,
    "vis_rag": "Red",
    "score_wind": 0.25,
    "score_rain": 0.4375
  },
  {
    "date": "2026-02-11",
    "period": "afternoon",
    "location_name": "towan_beach",
    "latitude": 50.157088,
    "longitude": -4.984155,
    "vis_score": 0.48840844654398125,
    "vis_rag": "Red",
    "score_wind": 0.0625,
    "score_rain": 0.6375
  },
  {
    "date": "2026-02-11",
    "period": "morning",
    "location_name": "towan_beach",
    "latitude": 50.157088,
    "longitude": -4.984155,
    "vis_score": 0.47782400311957035,
    "vis_rag": "Red",
    "score_wind": 0.875,
    "score_rain": 0.5625
  },
  {
    "date": "2026-02-12",
    "period": "afternoon",
    "location_name": "berry_head",
    "latitude": 50.402568,
    "longitude": -3.481143,
    "vis_score": 0.430057911630921,
    "vis_rag": "Red",
    "score_wind": 0.4375,
    "score_rain": 0.125
  },
  {
    "date": "2026-02-12",
    "period": "morning",
    "location_name": "berry_head",
    "latitude": 50.402568,
    "longitude": -3.481143,
    "vis_score": 0.48288706591275077,
    "vis_rag": "Red",
    "score_wind": 0.1875,
    "score_rain": 0.0
  },
  {
    "date": "2026-02-12",
    "period": "afternoon",
    "location_name": "branscombe",
    "latitude": 50.683979,
    "longitude": -3.116856,
    "vis_score": 0.35824800777783095,
    "vis_rag": "Red",
    "score_wind": 0.625,
    "score_rain": 0.0
  },
  {
    "date": "2026-02-12",
    "period": "morning",
    "location_name": "branscombe",
    "latitude": 50.683979,
    "longitude": -3.116856,
    "vis_score": 0.36892333693770524,
    "vis_rag": "Red",
    "score_wind": 0.375,
    "score_rain": 0.0
  },
  {
    "date": "2026-02-12",
    "period": "afternoon",
    "location_name": "bude",
    "latitude": 50.817853,
    "longitude": -4.560764,
    "vis_score": 0.38173401721538114,
    "vis_rag": "Red",
    "score_wind": 0.25,
    "score_rain": 0.6875
  },
  {
    "date": "2026-02-12",
    "period": "morning",
    "location_name": "bude",
    "latitude": 50.817853,
    "longitude": -4.560764,
    "vis_score": 0.37278795150795435,
    "vis_rag": "Red",
    "score_wind": 0.1875,
    "score_rain": 0.625
  },
  {
    "date": "2026-02-12",
    "period": "afternoon",
    "location_name": "dodman_point",
    "latitude": 50.222568,
    "longitude": -4.806776,
    "vis_score": 0.4433825589129901,
    "vis_rag": "Red",
    "score_wind": 0.875,
    "score_rain": 0.25
  },
  {
    "date": "2026-02-12",
    "period": "morning",
    "location_name": "dodman_point",
    "latitude": 50.222568,
    "longitude": -4.806776,
    "vis_score": 0.39236007718096455,
    "vis_rag": "Red",
    "score_wind": 0.875,
    "score_rain": 0.3125
  },
  {
    "date": "2026-02-12",
    "period": "afternoon",
    "location_name": "falmouth",
    "latitude": 50.152573,
    "longitude": -5.06627,
    "vis_score": 0.620352883176734,
    "vis_rag": "Red",
    "score_wind": 0.875,
    "score_rain": 0.3125
  },
  {
    "date": "2026-02-12",
    "period": "morning",
    "location_name": "falmouth",
    "latitude": 50.152573,
    "longitude": -5.06627,
    "vis_score": 0.5946624775484313,
    "vis_rag": "Red",
    "score_wind": 0.875,
    "score_rain": 0.4375
  },
  {
    "date": "2026-02-12",
    "period": "afternoon",
    "location_name": "fishermans_cove",
    "latitude": 50.238151,
    "longitude": -5.371382,
    "vis_score": 0.6397768681264809,
    "vis_rag": "Red",
    "score_wind": 0.875,
    "score_rain": 0.4375
  },
  {
    "date": "2026-02-12",
    "period": "morning",
    "location_name": "fishermans_cove",
    "latitude": 50.238151,
    "longitude": -5.371382,
    "vis_score": 0.6127184644907095,
    "vis_rag": "Red",
    "score_wind": 0.75,
    "score_rain": 0.5625
  },
  {
    "date": "2026-02-12",
    "period": "afternoon",
    "location_name": "isle_portland",
    "latitude": 50.521858,
    "longitude": -2.44875,
    "vis_score": 0.36229273438139203,
    "vis_rag": "Red",
    "score_wind": 0.25,
    "score_rain": 0.125
  },
  {
    "date": "2026-02-12",
    "period": "morning",
    "location_name": "isle_portland",
    "latitude": 50.521858,
    "longitude": -2.44875,
    "vis_score": 0.38939909417930973,
    "vis_rag": "Red",
    "score_wind": 0.5625,
    "score_rain": 0.1875
  },
  {
    "date": "2026-02-12",
    "period": "afternoon",
    "location_name": "lannacombe",
    "latitude": 50.221171,
    "longitude": -3.680452,
    "vis_score": 0.38403598134818007,
    "vis_rag": "Red",
    "score_wind": 0.75,
    "score_rain": 0.0
  },
  {
    "date": "2026-02-12",
    "period": "morning",
    "location_name": "lannacombe",
    "latitude": 50.221171,
    "longitude": -3.680452,
    "vis_score": 0.3797416378816893,
    "vis_rag": "Red",
    "score_wind": 0.5,
    "score_rain": 0.0
  },
  {
    "date": "2026-02-12",
    "period": "afternoon",
    "location_name": "start_point",
    "latitude": 50.229288,
    "longitude": -3.65076,
    "vis_score": 0.5234971059402571,
    "vis_rag": "Red",
    "score_wind": 0.75,
    "score_rain": 0.0
  },
  {
    "date": "2026-02-12",
    "period": "morning",
    "location_name": "start_point",
    "latitude": 50.229288,
    "longitude": -3.65076,
    "vis_score": 0.5548562134879618,
    "vis_rag": "Red",
    "score_wind": 0.5,
    "score_rain": 0.125
  },
  {
    "date": "2026-02-12",
    "period": "afternoon",
    "location_name": "thurlestone",
    "latitude": 50.263044,
    "longitude": -3.870057,
    "vis_score": 0.3136639271831212,
    "vis_rag": "Red",
    "score_wind": 0.1875,
    "score_rain": 0.0
  },
  {
    "date": "2026-02-12",
    "period": "morning",
    "location_name": "thurlestone",
    "latitude": 50.263044,
    "longitude": -3.870057,
    "vis_score": 0.36386561817498925,
    "vis_rag": "Red",
    "score_wind": 0.125,
    "score_rain": 0.1875
  },
  {
    "date": "2026-02-12",
    "period": "afternoon",
    "location_name": "towan_beach",
    "latitude": 50.157088,
    "longitude": -4.984155,
    "vis_score": 0.5201586891294526,
    "vis_rag": "Red",
    "score_wind": 0.875,
    "score_rain": 0.25
  },
  {
    "date": "2026-02-12",
    "period": "morning",
    "location_name": "towan_beach",
    "latitude": 50.157088,
    "longitude": -4.984155,
    "vis_score": 0.48779229887369996,
    "vis_rag": "Red",
    "score_wind": 0.875,
    "score_rain": 0.125
  },
  {
    "date": "2026-02-13",
    "period": "afternoon",
    "location_name": "berry_head",
    "latitude": 50.402568,
    "longitude": -3.481143,
    "vis_score": 0.2958546980003648,
    "vis_rag": "Amber",
    "score_wind": 0.25,
    "score_rain": 0.0
  },
  {
    "date": "2026-02-13",
    "period": "morning",
    "location_name": "berry_head",
    "latitude": 50.402568,
    "longitude": -3.481143,
    "vis_score": 0.3648649119120999,
    "vis_rag": "Red",
    "score_wind": 0.0625,
    "score_rain": 0.0
  },
  {
    "date": "2026-02-13",
    "period": "afternoon",
    "location_name": "branscombe",
    "latitude": 50.683979,
    "longitude": -3.116856,
    "vis_score": 0.30832298009923476,
    "vis_rag": "Red",
    "score_wind": 0.5,
    "score_rain": 0.125
  },
  {
    "date": "2026-02-13",
    "period": "morning",
    "location_name": "branscombe",
    "latitude": 50.683979,
    "longitude": -3.116856,
    "vis_score": 0.32516135002692526,
    "vis_rag": "Red",
    "score_wind": 0.5,
    "score_rain": 0.0
  },
  {
    "date": "2026-02-13",
    "period": "afternoon",
    "location_name": "bude",
    "latitude": 50.817853,
    "longitude": -4.560764,
    "vis_score": 0.30951124983560724,
    "vis_rag": "Red",
    "score_wind": 0.375,
    "score_rain": 0.375
  },
  {
    "date": "2026-02-13",
    "period": "morning",
    "location_name": "bude",
    "latitude": 50.817853,
    "longitude": -4.560764,
    "vis_score": 0.3528623293242945,
    "vis_rag": "Red",
    "score_wind": 0.0,
    "score_rain": 0.125
  },
  {
    "date": "2026-02-13",
    "period": "afternoon",
    "location_name": "dodman_point",
    "latitude": 50.222568,
    "longitude": -4.806776,
    "vis_score": 0.39770020977440235,
    "vis_rag": "Red",
    "score_wind": 0.625,
    "score_rain": 0.0
  },
  {
    "date": "2026-02-13",
    "period": "morning",
    "location_name": "dodman_point",
    "latitude": 50.222568,
    "longitude": -4.806776,
    "vis_score": 0.42587402309949496,
    "vis_rag": "Red",
    "score_wind": 0.5,
    "score_rain": 0.0
  },
  {
    "date": "2026-02-13",
    "period": "afternoon",
    "location_name": "falmouth",
    "latitude": 50.152573,
    "longitude": -5.06627,
    "vis_score": 0.5281199863091173,
    "vis_rag": "Red",
    "score_wind": 0.75,
    "score_rain": 0.125
  },
  {
    "date": "2026-02-13",
    "period": "morning",
    "location_name": "falmouth",
    "latitude": 50.152573,
    "longitude": -5.06627,
    "vis_score": 0.5709571545922624,
    "vis_rag": "Red",
    "score_wind": 0.5,
    "score_rain": 0.0
  },
  {
    "date": "2026-02-13",
    "period": "afternoon",
    "location_name": "fishermans_cove",
    "latitude": 50.238151,
    "longitude": -5.371382,
    "vis_score": 0.506687238708046,
    "vis_rag": "Red",
    "score_wind": 0.1875,
    "score_rain": 0.125
  },
  {
    "date": "2026-02-13",
    "period": "morning",
    "location_name": "fishermans_cove",
    "latitude": 50.238151,
    "longitude": -5.371382,
    "vis_score": 0.5884293651556288,
    "vis_rag": "Red",
    "score_wind": 0.375,
    "score_rain": 0.125
  },
  {
    "date": "2026-02-13",
    "period": "afternoon",
    "location_name": "isle_portland",
    "latitude": 50.521858,
    "longitude": -2.44875,
    "vis_score": 0.34422612045978246,
    "vis_rag": "Red",
    "score_wind": 1.0,
    "score_rain": 0.125
  },
  {
    "date": "2026-02-13",
    "period": "morning",
    "location_name": "isle_portland",
    "latitude": 50.521858,
    "longitude": -2.44875,
    "vis_score": 0.32651697006215485,
    "vis_rag": "Red",
    "score_wind": 0.4375,
    "score_rain": 0.0
  },
  {
    "date": "2026-02-13",
    "period": "afternoon",
    "location_name": "lannacombe",
    "latitude": 50.221171,
    "longitude": -3.680452,
    "vis_score": 0.31375567572802643,
    "vis_rag": "Red",
    "score_wind": 0.625,
    "score_rain": 0.0
  },
  {
    "date": "2026-02-13",
    "period": "morning",
    "location_name": "lannacombe",
    "latitude": 50.221171,
    "longitude": -3.680452,
    "vis_score": 0.3447949166552792,
    "vis_rag": "Red",
    "score_wind": 0.25,
    "score_rain": 0.0
  },
  {
    "date": "2026-02-13",
    "period": "afternoon",
    "location_name": "start_point",
    "latitude": 50.229288,
    "longitude": -3.65076,
    "vis_score": 0.38087352923838647,
    "vis_rag": "Red",
    "score_wind": 0.4375,
    "score_rain": 0.0
  },
  {
    "date": "2026-02-13",
    "period": "morning",
    "location_name": "start_point",
    "latitude": 50.229288,
    "longitude": -3.65076,
    "vis_score": 0.4481551906166117,
    "vis_rag": "Red",
    "score_wind": 0.25,
    "score_rain": 0.0
  },
  {
    "date": "2026-02-13",
    "period": "afternoon",
    "location_name": "thurlestone",
    "latitude": 50.263044,
    "longitude": -3.870057,
    "vis_score": 0.24470096091051752,
    "vis_rag": "Amber",
    "score_wind": 0.75,
    "score_rain": 0.0
  },
  {
    "date": "2026-02-13",
    "period": "morning",
    "location_name": "thurlestone",
    "latitude": 50.263044,
    "longitude": -3.870057,
    "vis_score": 0.25372337028597175,
    "vis_rag": "Amber",
    "score_wind": 0.25,
    "score_rain": 0.0
  },
  {
    "date": "2026-02-13",
    "period": "afternoon",
    "location_name": "towan_beach",
    "latitude": 50.157088,
    "longitude": -4.984155,
    "vis_score": 0.44889282353232257,
    "vis_rag": "Red",
    "score_wind": 0.75,
    "score_rain": 0.0
  },
  {
    "date": "2026-02-13",
    "period": "morning",
    "location_name": "towan_beach",
    "latitude": 50.157088,
    "longitude": -4.984155,
    "vis_score": 0.48585317469707373,
    "vis_rag": "Red",
    "score_wind": 0.5,
    "score_rain": 0.0
  },
  {
    "date": "2026-02-14",
    "period": "afternoon",
    "location_name": "berry_head",
    "latitude": 50.402568,
    "longitude": -3.481143,
    "vis_score": 0.17867017631635412,
    "vis_rag": "Amber",
    "score_wind": 0.0,
    "score_rain": 0.0
  },
  {
    "date": "2026-02-14",
    "period": "morning",
    "location_name": "berry_head",
    "latitude": 50.402568,
    "longitude": -3.481143,
    "vis_score": 0.2394860637492355,
    "vis_rag": "Amber",
    "score_wind": 0.25,
    "score_rain": 0.0
  },
  {
    "date": "2026-02-14",
    "period": "afternoon",
    "location_name": "branscombe",
    "latitude": 50.683979,
    "longitude": -3.116856,
    "vis_score": 0.2634376235822518,
    "vis_rag": "Amber",
    "score_wind": 0.125,
    "score_rain": 0.0
  },
  {
    "date": "2026-02-14",
    "period": "morning",
    "location_name": "branscombe",
    "latitude": 50.683979,
    "longitude": -3.116856,
    "vis_score": 0.29604493297618184,
    "vis_rag": "Amber",
    "score_wind": 0.5,
    "score_rain": 0.0
  },
  {
    "date": "2026-02-14",
    "period": "afternoon",
    "location_name": "bude",
    "latitude": 50.817853,
    "longitude": -4.560764,
    "vis_score": 0.2308099058818494,
    "vis_rag": "Amber",
    "score_wind": 0.125,
    "score_rain": 0.0
  },
  {
    "date": "2026-02-14",
    "period": "morning",
    "location_name": "bude",
    "latitude": 50.817853,
    "longitude": -4.560764,
    "vis_score": 0.29237570534003354,
    "vis_rag": "Amber",
    "score_wind": 0.125,
    "score_rain": 0.0
  },
  {
    "date": "2026-02-14",
    "period": "afternoon",
    "location_name": "dodman_point",
    "latitude": 50.222568,
    "longitude": -4.806776,
    "vis_score": 0.3384293390297563,
    "vis_rag": "Red",
    "score_wind": 0.25,
    "score_rain": 0.0
  },
  {
    "date": "2026-02-14",
    "period": "morning",
    "location_name": "dodman_point",
    "latitude": 50.222568,
    "longitude": -4.806776,
    "vis_score": 0.3764851550178445,
    "vis_rag": "Red",
    "score_wind": 0.5,
    "score_rain": 0.0
  },
  {
    "date": "2026-02-14",
    "period": "afternoon",
    "location_name": "falmouth",
    "latitude": 50.152573,
    "longitude": -5.06627,
    "vis_score": 0.404766211540944,
    "vis_rag": "Red",
    "score_wind": 0.25,
    "score_rain": 0.0
  },
  {
    "date": "2026-02-14",
    "period": "morning",
    "location_name": "falmouth",
    "latitude": 50.152573,
    "longitude": -5.06627,
    "vis_score": 0.4744306927174669,
    "vis_rag": "Red",
    "score_wind": 0.5,
    "score_rain": 0.0
  },
  {
    "date": "2026-02-14",
    "period": "afternoon",
    "location_name": "fishermans_cove",
    "latitude": 50.238151,
    "longitude": -5.371382,
    "vis_score": 0.3234969505399461,
    "vis_rag": "Red",
    "score_wind": 0.375,
    "score_rain": 0.0
  },
  {
    "date": "2026-02-14",
    "period": "morning",
    "location_name": "fishermans_cove",
    "latitude": 50.238151,
    "longitude": -5.371382,
    "vis_score": 0.40852552542724574,
    "vis_rag": "Red",
    "score_wind": 0.0,
    "score_rain": 0.125
  },
  {
    "date": "2026-02-14",
    "period": "afternoon",
    "location_name": "isle_portland",
    "latitude": 50.521858,
    "longitude": -2.44875,
    "vis_score": 0.3690664272528792,
    "vis_rag": "Red",
    "score_wind": 0.375,
    "score_rain": 0.0
  },
  {
    "date": "2026-02-14",
    "period": "morning",
    "location_name": "isle_portland",
    "latitude": 50.521858,
    "longitude": -2.44875,
    "vis_score": 0.37513202852834815,
    "vis_rag": "Red",
    "score_wind": 1.0,
    "score_rain": 0.0
  },
  {
    "date": "2026-02-14",
    "period": "afternoon",
    "location_name": "lannacombe",
    "latitude": 50.221171,
    "longitude": -3.680452,
    "vis_score": 0.26504861740391633,
    "vis_rag": "Amber",
    "score_wind": 0.125,
    "score_rain": 0.0
  },
  {
    "date": "2026-02-14",
    "period": "morning",
    "location_name": "lannacombe",
    "latitude": 50.221171,
    "longitude": -3.680452,
    "vis_score": 0.30127642078279326,
    "vis_rag": "Red",
    "score_wind": 0.5,
    "score_rain": 0.0
  },
  {
    "date": "2026-02-14",
    "period": "afternoon",
    "location_name": "start_point",
    "latitude": 50.229288,
    "longitude": -3.65076,
    "vis_score": 0.2783475480083919,
    "vis_rag": "Amber",
    "score_wind": 0.25,
    "score_rain": 0.0
  },
  {
    "date": "2026-02-14",
    "period": "morning",
    "location_name": "start_point",
    "latitude": 50.229288,
    "longitude": -3.65076,
    "vis_score": 0.329459623085798,
    "vis_rag": "Red",
    "score_wind": 0.5,
    "score_rain": 0.0
  },
  {
    "date": "2026-02-14",
    "period": "afternoon",
    "location_name": "thurlestone",
    "latitude": 50.263044,
    "longitude": -3.870057,
    "vis_score": 0.23545677164528436,
    "vis_rag": "Amber",
    "score_wind": 0.125,
    "score_rain": 0.0
  },
  {
    "date": "2026-02-14",
    "period": "morning",
    "location_name": "thurlestone",
    "latitude": 50.263044,
    "longitude": -3.870057,
    "vis_score": 0.25837292469834655,
    "vis_rag": "Amber",
    "score_wind": 0.625,
    "score_rain": 0.0
  },
  {
    "date": "2026-02-14",
    "period": "afternoon",
    "location_name": "towan_beach",
    "latitude": 50.157088,
    "longitude": -4.984155,
    "vis_score": 0.36131008130254005,
    "vis_rag": "Red",
    "score_wind": 0.25,
    "score_rain": 0.0
  },
  {
    "date": "2026-02-14",
    "period": "morning",
    "location_name": "towan_beach",
    "latitude": 50.157088,
    "longitude": -4.984155,
    "vis_score": 0.4136953267364662,
    "vis_rag": "Red",
    "score_wind": 0.5,
    "score_rain": 0.0
  },
  {
    "date": "2026-02-15",
    "period": "afternoon",
    "location_name": "berry_head",
    "latitude": 50.402568,
    "longitude": -3.481143,
    "vis_score": 0.3188763231783185,
    "vis_rag": "Red",
    "score_wind": 1.0,
    "score_rain": 0.875
  },
  {
    "date": "2026-02-15",
    "period": "morning",
    "location_name": "berry_head",
    "latitude": 50.402568,
    "longitude": -3.481143,
    "vis_score": 0.19684975987344205,
    "vis_rag": "Amber",
    "score_wind": 0.5,
    "score_rain": 0.8125
  },
  {
    "date": "2026-02-15",
    "period": "afternoon",
    "location_name": "branscombe",
    "latitude": 50.683979,
    "longitude": -3.116856,
    "vis_score": 0.3002164787291726,
    "vis_rag": "Red",
    "score_wind": 0.25,
    "score_rain": 0.8125
  },
  {
    "date": "2026-02-15",
    "period": "morning",
    "location_name": "branscombe",
    "latitude": 50.683979,
    "longitude": -3.116856,
    "vis_score": 0.25163024362639,
    "vis_rag": "Amber",
    "score_wind": 0.25,
    "score_rain": 0.625
  },
  {
    "date": "2026-02-15",
    "period": "afternoon",
    "location_name": "bude",
    "latitude": 50.817853,
    "longitude": -4.560764,
    "vis_score": 0.3152050487601103,
    "vis_rag": "Red",
    "score_wind": 0.25,
    "score_rain": 0.7625
  },
  {
    "date": "2026-02-15",
    "period": "morning",
    "location_name": "bude",
    "latitude": 50.817853,
    "longitude": -4.560764,
    "vis_score": 0.2705831427002565,
    "vis_rag": "Amber",
    "score_wind": 0.4375,
    "score_rain": 0.875
  },
  {
    "date": "2026-02-15",
    "period": "afternoon",
    "location_name": "dodman_point",
    "latitude": 50.222568,
    "longitude": -4.806776,
    "vis_score": 0.3682837679568353,
    "vis_rag": "Red",
    "score_wind": 0.25,
    "score_rain": 0.75
  },
  {
    "date": "2026-02-15",
    "period": "morning",
    "location_name": "dodman_point",
    "latitude": 50.222568,
    "longitude": -4.806776,
    "vis_score": 0.33980518369416846,
    "vis_rag": "Red",
    "score_wind": 0.25,
    "score_rain": 0.9375
  },
  {
    "date": "2026-02-15",
    "period": "afternoon",
    "location_name": "falmouth",
    "latitude": 50.152573,
    "longitude": -5.06627,
    "vis_score": 0.4735942564501143,
    "vis_rag": "Red",
    "score_wind": 1.0,
    "score_rain": 0.75
  },
  {
    "date": "2026-02-15",
    "period": "morning",
    "location_name": "falmouth",
    "latitude": 50.152573,
    "longitude": -5.06627,
    "vis_score": 0.39481243875306404,
    "vis_rag": "Red",
    "score_wind": 0.625,
    "score_rain": 0.9375
  },
  {
    "date": "2026-02-15",
    "period": "afternoon",
    "location_name": "fishermans_cove",
    "latitude": 50.238151,
    "longitude": -5.371382,
    "vis_score": 0.4544768140330745,
    "vis_rag": "Red",
    "score_wind": 1.0,
    "score_rain": 0.75
  },
  {
    "date": "2026-02-15",
    "period": "morning",
    "location_name": "fishermans_cove",
    "latitude": 50.238151,
    "longitude": -5.371382,
    "vis_score": 0.3650590786029909,
    "vis_rag": "Red",
    "score_wind": 1.0,
    "score_rain": 0.875
  },
  {
    "date": "2026-02-15",
    "period": "afternoon",
    "location_name": "isle_portland",
    "latitude": 50.521858,
    "longitude": -2.44875,
    "vis_score": 0.3842889876582456,
    "vis_rag": "Red",
    "score_wind": 0.25,
    "score_rain": 0.75
  },
  {
    "date": "2026-02-15",
    "period": "morning",
    "location_name": "isle_portland",
    "latitude": 50.521858,
    "longitude": -2.44875,
    "vis_score": 0.3550130176575495,
    "vis_rag": "Red",
    "score_wind": 0.25,
    "score_rain": 0.625
  },
  {
    "date": "2026-02-15",
    "period": "afternoon",
    "location_name": "lannacombe",
    "latitude": 50.221171,
    "longitude": -3.680452,
    "vis_score": 0.3163718453512243,
    "vis_rag": "Red",
    "score_wind": 0.25,
    "score_rain": 0.6875
  },
  {
    "date": "2026-02-15",
    "period": "morning",
    "location_name": "lannacombe",
    "latitude": 50.221171,
    "longitude": -3.680452,
    "vis_score": 0.2606699106789425,
    "vis_rag": "Amber",
    "score_wind": 0.1875,
    "score_rain": 0.875
  },
  {
    "date": "2026-02-15",
    "period": "afternoon",
    "location_name": "start_point",
    "latitude": 50.229288,
    "longitude": -3.65076,
    "vis_score": 0.4370342777230481,
    "vis_rag": "Red",
    "score_wind": 1.0,
    "score_rain": 0.6875
  },
  {
    "date": "2026-02-15",
    "period": "morning",
    "location_name": "start_point",
    "latitude": 50.229288,
    "longitude": -3.65076,
    "vis_score": 0.31995137639132176,
    "vis_rag": "Red",
    "score_wind": 1.0,
    "score_rain": 0.8125
  },
  {
    "date": "2026-02-15",
    "period": "afternoon",
    "location_name": "thurlestone",
    "latitude": 50.263044,
    "longitude": -3.870057,
    "vis_score": 0.2976003372379244,
    "vis_rag": "Amber",
    "score_wind": 0.25,
    "score_rain": 0.625
  },
  {
    "date": "2026-02-15",
    "period": "morning",
    "location_name": "thurlestone",
    "latitude": 50.263044,
    "longitude": -3.870057,
    "vis_score": 0.24533211977008507,
    "vis_rag": "Amber",
    "score_wind": 0.25,
    "score_rain": 0.75
  },
  {
    "date": "2026-02-15",
    "period": "afternoon",
    "location_name": "towan_beach",
    "latitude": 50.157088,
    "longitude": -4.984155,
    "vis_score": 0.4386919267853382,
    "vis_rag": "Red",
    "score_wind": 1.0,
    "score_rain": 0.75
  },
  {
    "date": "2026-02-15",
    "period": "morning",
    "location_name": "towan_beach",
    "latitude": 50.157088,
    "longitude": -4.984155,
    "vis_score": 0.35701248800500207,
    "vis_rag": "Red",
    "score_wind": 0.4375,
    "score_rain": 0.9375
  },
  {
    "date": "2026-02-16",
    "period": "afternoon",
    "location_name": "berry_head",
    "latitude": 50.402568,
    "longitude": -3.481143,
    "vis_score": 0.4327447915552243,
    "vis_rag": "Red",
    "score_wind": 0.5625,
    "score_rain": 0.0
  },
  {
    "date": "2026-02-16",
    "period": "morning",
    "location_name": "berry_head",
    "latitude": 50.402568,
    "longitude": -3.481143,
    "vis_score": 0.4020360484264974,
    "vis_rag": "Red",
    "score_wind": 1.0,
    "score_rain": 0.0
  },
  {
    "date": "2026-02-16",
    "period": "afternoon",
    "location_name": "branscombe",
    "latitude": 50.683979,
    "longitude": -3.116856,
    "vis_score": 0.28905119109687794,
    "vis_rag": "Amber",
    "score_wind": 0.75,
    "score_rain": 0.0
  },
  {
    "date": "2026-02-16",
    "period": "morning",
    "location_name": "branscombe",
    "latitude": 50.683979,
    "longitude": -3.116856,
    "vis_score": 0.2862566709878891,
    "vis_rag": "Amber",
    "score_wind": 0.0625,
    "score_rain": 0.0
  },
  {
    "date": "2026-02-16",
    "period": "afternoon",
    "location_name": "bude",
    "latitude": 50.817853,
    "longitude": -4.560764,
    "vis_score": 0.3967161770520483,
    "vis_rag": "Red",
    "score_wind": 0.25,
    "score_rain": 0.6875
  },
  {
    "date": "2026-02-16",
    "period": "morning",
    "location_name": "bude",
    "latitude": 50.817853,
    "longitude": -4.560764,
    "vis_score": 0.3593482866277902,
    "vis_rag": "Red",
    "score_wind": 0.25,
    "score_rain": 0.75
  },
  {
    "date": "2026-02-16",
    "period": "afternoon",
    "location_name": "dodman_point",
    "latitude": 50.222568,
    "longitude": -4.806776,
    "vis_score": 0.33043914252189116,
    "vis_rag": "Red",
    "score_wind": 0.8125,
    "score_rain": 0.0
  },
  {
    "date": "2026-02-16",
    "period": "morning",
    "location_name": "dodman_point",
    "latitude": 50.222568,
    "longitude": -4.806776,
    "vis_score": 0.3482896521156632,
    "vis_rag": "Red",
    "score_wind": 0.25,
    "score_rain": 0.0
  },
  {
    "date": "2026-02-16",
    "period": "afternoon",
    "location_name": "falmouth",
    "latitude": 50.152573,
    "longitude": -5.06627,
    "vis_score": 0.5239779415025947,
    "vis_rag": "Red",
    "score_wind": 1.0,
    "score_rain": 0.0
  },
  {
    "date": "2026-02-16",
    "period": "morning",
    "location_name": "falmouth",
    "latitude": 50.152573,
    "longitude": -5.06627,
    "vis_score": 0.5123797446838203,
    "vis_rag": "Red",
    "score_wind": 1.0,
    "score_rain": 0.0
  },
  {
    "date": "2026-02-16",
    "period": "afternoon",
    "location_name": "fishermans_cove",
    "latitude": 50.238151,
    "longitude": -5.371382,
    "vis_score": 0.6219083173034425,
    "vis_rag": "Red",
    "score_wind": 1.0,
    "score_rain": 0.5
  },
  {
    "date": "2026-02-16",
    "period": "morning",
    "location_name": "fishermans_cove",
    "latitude": 50.238151,
    "longitude": -5.371382,
    "vis_score": 0.5472333745155427,
    "vis_rag": "Red",
    "score_wind": 1.0,
    "score_rain": 0.75
  },
  {
    "date": "2026-02-16",
    "period": "afternoon",
    "location_name": "isle_portland",
    "latitude": 50.521858,
    "longitude": -2.44875,
    "vis_score": 0.31954690216723136,
    "vis_rag": "Red",
    "score_wind": 0.25,
    "score_rain": 0.0
  },
  {
    "date": "2026-02-16",
    "period": "morning",
    "location_name": "isle_portland",
    "latitude": 50.521858,
    "longitude": -2.44875,
    "vis_score": 0.3660177082238606,
    "vis_rag": "Red",
    "score_wind": 0.25,
    "score_rain": 0.0
  },
  {
    "date": "2026-02-16",
    "period": "afternoon",
    "location_name": "lannacombe",
    "latitude": 50.221171,
    "longitude": -3.680452,
    "vis_score": 0.3843114395153219,
    "vis_rag": "Red",
    "score_wind": 0.875,
    "score_rain": 0.0
  },
  {
    "date": "2026-02-16",
    "period": "morning",
    "location_name": "lannacombe",
    "latitude": 50.221171,
    "longitude": -3.680452,
    "vis_score": 0.346608210646238,
    "vis_rag": "Red",
    "score_wind": 1.0,
    "score_rain": 0.0
  },
  {
    "date": "2026-02-16",
    "period": "afternoon",
    "location_name": "start_point",
    "latitude": 50.229288,
    "longitude": -3.65076,
    "vis_score": 0.5093234964178738,
    "vis_rag": "Red",
    "score_wind": 0.875,
    "score_rain": 0.0
  },
  {
    "date": "2026-02-16",
    "period": "morning",
    "location_name": "start_point",
    "latitude": 50.229288,
    "longitude": -3.65076,
    "vis_score": 0.48499256968556104,
    "vis_rag": "Red",
    "score_wind": 1.0,
    "score_rain": 0.0
  },
  {
    "date": "2026-02-16",
    "period": "afternoon",
    "location_name": "thurlestone",
    "latitude": 50.263044,
    "longitude": -3.870057,
    "vis_score": 0.26398389523891963,
    "vis_rag": "Amber",
    "score_wind": 0.25,
    "score_rain": 0.0
  },
  {
    "date": "2026-02-16",
    "period": "morning",
    "location_name": "thurlestone",
    "latitude": 50.263044,
    "longitude": -3.870057,
    "vis_score": 0.28965572768407005,
    "vis_rag": "Amber",
    "score_wind": 0.25,
    "score_rain": 0.0
  },
  {
    "date": "2026-02-16",
    "period": "afternoon",
    "location_name": "towan_beach",
    "latitude": 50.157088,
    "longitude": -4.984155,
    "vis_score": 0.5046490935688914,
    "vis_rag": "Red",
    "score_wind": 1.0,
    "score_rain": 0.0
  },
  {
    "date": "2026-02-16",
    "period": "morning",
    "location_name": "towan_beach",
    "latitude": 50.157088,
    "longitude": -4.984155,
    "vis_score": 0.4865060781773406,
    "vis_rag": "Red",
    "score_wind": 1.0,
    "score_rain": 0.0
  },
  {
    "date": "2026-02-17",
    "period": "morning",
    "location_name": "berry_head",
    "latitude": 50.402568,
    "longitude": -3.481143,
    "vis_score": 0.4157617110365842,
    "vis_rag": "Red",
    "score_wind": 0.25,
    "score_rain": 0.0
  },
  {
    "date": "2026-02-17",
    "period": "morning",
    "location_name": "branscombe",
    "latitude": 50.683979,
    "longitude": -3.116856,
    "vis_score": 0.2889614235737432,
    "vis_rag": "Amber",
    "score_wind": 0.5,
    "score_rain": 0.0
  },
  {
    "date": "2026-02-17",
    "period": "morning",
    "location_name": "bude",
    "latitude": 50.817853,
    "longitude": -4.560764,
    "vis_score": 0.4165805265497143,
    "vis_rag": "Red",
    "score_wind": 0.25,
    "score_rain": 0.75
  },
  {
    "date": "2026-02-17",
    "period": "morning",
    "location_name": "dodman_point",
    "latitude": 50.222568,
    "longitude": -4.806776,
    "vis_score": 0.3374114323885691,
    "vis_rag": "Red",
    "score_wind": 0.5,
    "score_rain": 0.0
  },
  {
    "date": "2026-02-17",
    "period": "morning",
    "location_name": "falmouth",
    "latitude": 50.152573,
    "longitude": -5.06627,
    "vis_score": 0.5178351357360409,
    "vis_rag": "Red",
    "score_wind": 0.5,
    "score_rain": 0.0
  },
  {
    "date": "2026-02-17",
    "period": "morning",
    "location_name": "fishermans_cove",
    "latitude": 50.238151,
    "longitude": -5.371382,
    "vis_score": 0.6469405448541778,
    "vis_rag": "Red",
    "score_wind": 0.5,
    "score_rain": 0.5
  },
  {
    "date": "2026-02-17",
    "period": "morning",
    "location_name": "isle_portland",
    "latitude": 50.521858,
    "longitude": -2.44875,
    "vis_score": 0.29095502107482013,
    "vis_rag": "Amber",
    "score_wind": 0.25,
    "score_rain": 0.0
  },
  {
    "date": "2026-02-17",
    "period": "morning",
    "location_name": "lannacombe",
    "latitude": 50.221171,
    "longitude": -3.680452,
    "vis_score": 0.386453383584521,
    "vis_rag": "Red",
    "score_wind": 0.5,
    "score_rain": 0.0
  },
  {
    "date": "2026-02-17",
    "period": "morning",
    "location_name": "start_point",
    "latitude": 50.229288,
    "longitude": -3.65076,
    "vis_score": 0.5010721014741263,
    "vis_rag": "Red",
    "score_wind": 0.5,
    "score_rain": 0.0
  },
  {
    "date": "2026-02-17",
    "period": "morning",
    "location_name": "thurlestone",
    "latitude": 50.263044,
    "longitude": -3.870057,
    "vis_score": 0.24088818980802645,
    "vis_rag": "Amber",
    "score_wind": 0.0,
    "score_rain": 0.0
  },
  {
    "date": "2026-02-17",
    "period": "morning",
    "location_name": "towan_beach",
    "latitude": 50.157088,
    "longitude": -4.984155,
    "vis_score": 0.5017720662401379,
    "vis_rag": "Red",
    "score_wind": 0.5,
    "score_rain": 0.0
  }
]